pc.sv
module pc (
	input [3:0] pc_in,
	input pc_clk,
	input pc_enb,
	input pc_rst,
	output reg [3:0] pc_out
	);

	reg [3:0] store;

	always @(posedge pc_clk or negedge pc_rst) begin
		if (!pc_rst) begin
			store <= 4'b0000; end
		else if (pc_enb) begin
			store <= pc_in; end
		else begin
			store <= store + 4'b0001; end

		pc_out <= store;
		end

		endmodule

tb_pc.sv
`timescale 1ns/1ps

module tb_pc;

reg [3:0] in_tb;
reg clk_tb;
reg enb_tb;
reg rst_tb;
wire [3:0] out_tb;

pc UUT (
	.pc_in (in_tb),
	.pc_clk (clk_tb),
	.pc_enb (enb_tb),
	.pc_rst (rst_tb),
	.pc_out (out_tb)
	);

	initial begin
		clk_tb = 1'b0;
		forever #5 clk_tb = ~clk_tb;
	end

	initial begin
		$dumpfile("pc.vcd");
		$dumpvars(0, tb_pc);

		$display("Time\tClk\tReset\tEnable\tAdress\tOutput");
		$display("---------------------------------------------------");
        
        // Initial phase
		in_tb = 4'hF; enb_tb = 1'b0; rst_tb = 1'b1;

        // Enable reset (active-low)
        #1;
        rst_tb = 1'b0; // (Enable asynchronous reset)
        $display("%0t\t%b\t%b\t%b\t%b\t%b", $time, clk_tb, rst_tb, enb_tb, in_tb, out_tb);
        #10;
        rst_tb = 1'b1; // (Diable reset)
        $display("%0t\t%b\t%b\t%b\t%b\t%b", $time, clk_tb, rst_tb, enb_tb, in_tb, out_tb);
        

        // Scenario 1: Normal incrementing
        #4; //Clock edge 1
        $display("%0t\t%b\t%b\t%b\t%b\t%b", $time, clk_tb, rst_tb, enb_tb, in_tb, out_tb);
        #10; //Clock edge 2
        $display("%0t\t%b\t%b\t%b\t%b\t%b", $time, clk_tb, rst_tb, enb_tb, in_tb, out_tb);
        #10; //Clock edge 3
        $display("%0t\t%b\t%b\t%b\t%b\t%b", $time, clk_tb, rst_tb, enb_tb, in_tb, out_tb);
        #10; //Clock edge 4
        $display("%0t\t%b\t%b\t%b\t%b\t%b", $time, clk_tb, rst_tb, enb_tb, in_tb, out_tb);
        
        // Scenario 2: Synchronous Load (Jump/Branch)
        #1;
        in_tb = 4'b1100; // Load new adress
        enb_tb = 1'b1; // Enable writing
        $display("%0t\t%b\t%b\t%b\t%b\t%b", $time, clk_tb, rst_tb, enb_tb, in_tb, out_tb);
        #9; // Clock edge 
        $display("%0t\t%b\t%b\t%b\t%b\t%b", $time, clk_tb, rst_tb, enb_tb, in_tb, out_tb);
        #10; // Next clock edge 
        $display("%0t\t%b\t%b\t%b\t%b\t%b", $time, clk_tb, rst_tb, enb_tb, in_tb, out_tb);
        
        // Scenario 3: Increment after load
        #1;
        in_tb = 4'hF; // New adress
        enb_tb = 1'b0; // Disable writing
        $display("%0t\t%b\t%b\t%b\t%b\t%b", $time, clk_tb, rst_tb, enb_tb, in_tb, out_tb);
        #9; // Clock edge 
        $display("%0t\t%b\t%b\t%b\t%b\t%b", $time, clk_tb, rst_tb, enb_tb, in_tb, out_tb);
        #10; // Next clock edge 
        $display("%0t\t%b\t%b\t%b\t%b\t%b", $time, clk_tb, rst_tb, enb_tb, in_tb, out_tb);

        // Scenario 4: Reset during Incrementation
        #1;
        rst_tb = 1'b0; // Activating Reset
        $display("%0t\t%b\t%b\t%b\t%b\t%b", $time, clk_tb, rst_tb, enb_tb, in_tb, out_tb);
        #9; // Clock edge 
        $display("%0t\t%b\t%b\t%b\t%b\t%b", $time, clk_tb, rst_tb, enb_tb, in_tb, out_tb);

        $display("Simulation finished");
        $finish;
end
endmodule

pc.vcd
$date
	Mon Jul  7 18:19:03 2025
$end
$version
	Icarus Verilog
$end
$timescale
	1ps
$end
$scope module tb_pc $end
$var wire 4 ! out_tb [3:0] $end
$var reg 1 " clk_tb $end
$var reg 1 # enb_tb $end
$var reg 4 $ in_tb [3:0] $end
$var reg 1 % rst_tb $end
$scope module UUT $end
$var wire 1 " pc_clk $end
$var wire 1 # pc_enb $end
$var wire 4 & pc_in [3:0] $end
$var wire 1 % pc_rst $end
$var reg 4 ' pc_out [3:0] $end
$var reg 4 ( store [3:0] $end
$upscope $end
$upscope $end
$enddefinitions $end
$comment Show the parameter values. $end
$dumpall
$end
#0
$dumpvars
bx (
bx '
b1111 &
1%
b1111 $
0#
0"
bx !
$end
#1000
b0 (
0%
#5000
b0 !
b0 '
1"
#10000
0"
#11000
1%
#15000
b1 (
1"
#20000
0"
#25000
b1 !
b1 '
b10 (
1"
#30000
0"
#35000
b10 !
b10 '
b11 (
1"
#40000
0"
#45000
b11 !
b11 '
b100 (
1"
#46000
1#
b1100 $
b1100 &
#50000
0"
#55000
b100 !
b100 '
b1100 (
1"
#60000
0"
#65000
b1100 !
b1100 '
1"
#66000
0#
b1111 $
b1111 &
#70000
0"
#75000
b1101 (
1"
#80000
0"
#85000
b1101 !
b1101 '
b1110 (
1"
#86000
b1110 !
b1110 '
b0 (
0%
#90000
0"
#95000
b0 !
b0 '
1"
