register.sv
module register(
	input [3:0] r_in,
	input r_clk,
	input r_enb,
	output reg [3:0] r_out
	);
	
	reg [3:0] r_str;

	always @(posedge r_clk) begin
		if (r_enb) begin
			r_str <= r_in; end
		
		r_out <= r_str;
		end
		endmodule

tb_register.sv
`timescale 1ns/1ps

module tb_register;

reg [3:0] in_tb;
reg clk_tb;
reg enb_tb;
wire [3:0] out_tb;

register UUT (
	.r_in (in_tb),
	.r_clk (clk_tb),
	.r_enb (enb_tb),
	.r_out (out_tb)
	);

	initial begin
		clk_tb = 1'b0;
		forever #5 clk_tb = ~clk_tb;
	end

	initial begin 
		$dumpfile("register.vcd");
		$dumpvars(0, tb_register);
		$display("Time\tclk\tinput\tenable\toutput");
		$display("------------------------------------------------");
        
        //Initial State (t=0)
		in_tb = 4'b0000; enb_tb = 1'b0; #1;
		$display("%0t\t%b\t%b\t%b\t%b", $time, clk_tb, in_tb, enb_tb, out_tb);
        // Scenario 1: First Load (load 1010)
		#9;
		in_tb = 4'b1010; // Data to load
        	enb_tb = 1'b1; // Enable write
        	#10;
		$display("%0t\t%b\t%b\t%b\t%b", $time, clk_tb, in_tb, enb_tb, out_tb);
		
        // Scenairo 2: Hold Value
        	#10;
		in_tb = 4'b0110; // Change input data
        	enb_tb = 1'b0; // Disable write
        	#10;
		$display("%0t\t%b\t%b\t%b\t%b", $time, clk_tb, in_tb, enb_tb, out_tb);

        // Scenario 3: Load again (load 0011)
        	#10;		
		in_tb = 4'b0011; // New data to load
		enb_tb = 1'b1; // Enable write
        	#10;
        	$display("%0t\t%b\t%b\t%b\t%b", $time, clk_tb, in_tb, enb_tb, out_tb);

        // Scenario 4: Change input while write disabled
        	#10;		
		enb_tb = 1'b0; // Disable write
        	in_tb = 4'b1111; // Change input
        	#5;
        	in_tb = 4'b0000; // Change input again
        	#5;
        	$display("%0t\t%b\t%b\t%b\t%b", $time, clk_tb, in_tb, enb_tb, out_tb);

        	$display("------------------------------------------------");
		$display("Simulation finished");
		$finish;
	end
	endmodule

register.vcd
$date
	Mon Jul  7 15:21:06 2025
$end
$version
	Icarus Verilog
$end
$timescale
	1ps
$end
$scope module tb_register $end
$var wire 4 ! out_tb [3:0] $end
$var reg 1 " clk_tb $end
$var reg 1 # enb_tb $end
$var reg 4 $ in_tb [3:0] $end
$scope module UUT $end
$var wire 1 " r_clk $end
$var wire 1 # r_enb $end
$var wire 4 % r_in [3:0] $end
$var reg 4 & r_out [3:0] $end
$var reg 4 ' r_str [3:0] $end
$upscope $end
$upscope $end
$enddefinitions $end
$comment Show the parameter values. $end
$dumpall
$end
#0
$dumpvars
bx '
bx &
b0 %
b0 $
0#
0"
bx !
$end
#5000
1"
#10000
0"
1#
b1010 $
b1010 %
#15000
b1010 '
1"
#20000
0"
#25000
b1010 !
b1010 &
1"
#30000
0"
0#
b110 $
b110 %
#35000
1"
#40000
0"
#45000
1"
#50000
0"
1#
b11 $
b11 %
#55000
b11 '
1"
#60000
0"
#65000
b11 !
b11 &
1"
#70000
0"
b1111 $
b1111 %
0#
#75000
1"
b0 $
b0 %
